MANIFEST.in
_.release.json
readme.md
requirements.txt
setup.py
pyco_sqlalchemy/__init__.py
pyco_sqlalchemy/_flask.py
pyco_sqlalchemy/_types.py
pyco_sqlalchemy/regex.py
pyco_sqlalchemy/utils.py
pyco_sqlalchemy.egg-info/PKG-INFO
pyco_sqlalchemy.egg-info/SOURCES.txt
pyco_sqlalchemy.egg-info/dependency_links.txt
pyco_sqlalchemy.egg-info/not-zip-safe
pyco_sqlalchemy.egg-info/requires.txt
pyco_sqlalchemy.egg-info/top_level.txt
tests/test_flask.py